Workbook

Sheet Overview
A1: Loss calculation walkthrough | R1: Chart data
A2: Every claim in the run. The Calculation tab works twenty of them through line by line.
A3: Area cap (m2) | B3: 4000 | R3: Claims by settlement ($) | S3: Liquefaction only | T3: Retaining wall only | U3: Both | V3: Total
A4: Retaining wall sub-cap per dwelling, incl GST ($) | B4: 57500 | R4: 0-0.5k | S4: 849 | T4: 0 | U4: 0 | V4: 849
A5: Land excess, share of what is payable | B5: 0.1 | R5: 0.5-1k | S5: 0 | T5: 0 | U5: 0 | V5: 0
A6: Land excess floor, per claim ($) | B6: 500 | R6: 1-2.5k | S6: 676 | T6: 1 | U6: 0 | V6: 677
A7: Land excess ceiling ($) | B7: 5000 | R7: 2.5-5k | S7: 191 | T7: 12 | U7: 4 | V7: 207
A8: Timber pole average rate, for reference ($/m2) | B8: 766.6375 | R8: 5-10k | S8: 0 | T8: 59 | U8: 14 | V8: 73
A9: GST rate | B9: 0.15 | R9: 10-25k | S9: 0 | T9: 290 | U9: 76 | V9: 366
A10: Across the whole run | R10: 25-50k | S10: 0 | T10: 70 | U10: 28 | V10: 98
A11: Claims | B11: 4388 | R11: over 50k | S11: 0 | T11: 2 | U11: 11 | V11: 13
A12: Claims paid anything | B12: 2283
A13: Total settlement ($) | B13: 13028776
A14: Median settlement, of those paid ($) | B14: 1225 | R14: Claims by repair cost ($) | S14: Liquefaction only | T14: Retaining wall only | U14: Both | V14: Total
A15: Total repair cost ($) | B15: 20735244 | R15: 0-0.5k | S15: 635 | T15: 0 | U15: 0 | V15: 635
A16: Claims where the cap binds and there is damaged land | B16: 11 | R16: 0.5-1k | S16: 849 | T16: 0 | U16: 0 | V16: 849
R17: 1-2.5k | S17: 581 | T17: 0 | U17: 0 | V17: 581
A18: The cap binds on many more claims than that, but only these have damaged land. On the rest the cap is the wall's value and the repair is that value plus the allowances, so it caps by arithmetic rather than as a result. | R18: 2.5-5k | S18: 286 | T18: 0 | U18: 0 | V18: 286
R19: 5-10k | S19: 0 | T19: 1 | U19: 1 | V19: 2
R20: 10-25k | S20: 0 | T20: 146 | U20: 77 | V20: 223
R21: 25-50k | S21: 0 | T21: 248 | U21: 42 | V21: 290
R22: over 50k | S22: 0 | T22: 40 | U22: 13 | V22: 53
R25: Claims by land cover cap ($) | S25: Liquefaction only | T25: Retaining wall only | U25: Both | V25: Total
R26: 0-100k | S26: 1 | T26: 434 | U26: 33 | V26: 468
R27: 100-250k | S27: 104 | T27: 1 | U27: 14 | V27: 119
R28: 250-500k | S28: 660 | T28: 0 | U28: 39 | V28: 699
R29: 500-750k | S29: 537 | T29: 0 | U29: 28 | V29: 565
R30: 750k-1m | S30: 221 | T30: 0 | U30: 9 | V30: 230
R31: 1-2m | S31: 128 | T31: 0 | U31: 3 | V31: 131
R32: over 2m | S32: 65 | T32: 0 | U32: 7 | V32: 72
R35: Repair cost by line ($) | S35: Total ($)
R36: Walls replaced | S36: 12632220
R37: New walls | S37: 1114733.4
R38: Spoil cleared | S38: 492687.66
R39: Fees | S39: 3562987.5
R40: Liquefaction | S40: 2932615
R41: Crossings | S41: 0

Sheet Calculation
A1: Loss calculation walkthrough
A2: Twenty claims chosen to show one of each case, not sampled at random. Yellow cells are the policy settings the run used.
A3: Area cap (m2) | B3: 4000
A4: Retaining wall sub-cap per dwelling, incl GST ($) | B4: 57500
A5: Land excess, share of what is payable | B5: 0.1
A6: Land excess floor, per claim ($) | B6: 500
A7: Land excess ceiling ($) | B7: 5000
A8: Timber pole average rate, for reference ($/m2) | B8: 766.6375
A9: GST rate | B9: 0.15
A12: Claim | B12: Dwellings | C12: Damaged land, for the cap (m2) | D12: Land rate incl GST ($/m2) | E12: Land value ($) | F12: Wall UDV ($) | G12: Wall to cap ($) | H12: Land cover cap ($) | I12: Repair cost ($) | J12: Payable before excess ($) | K12: Excess ($) | L12: Settlement ($) | M12: Why this claim
C13: whole insured area where liquefied, else the slip | E13: MIN(damaged land, area cap) x land rate | F13: face area x wall rate x GST; see the Repair cost tab | G13: MIN(wall UDV, sub-cap x dwellings) | H13: land value + wall to cap | J13: MIN(repair cost, cap) -- the Act pays the lesser | K13: a share of what is payable, floored and capped | L13: payable less the excess, never below zero
A14: 03dc0301-b79a-4927-9dc7-cd7e95fc9aaf | B14: 1 | C14: 3.9942764 | D14: 906.91537 | E14: =MIN(C14,$B$3)*D14 | F14: 10148.858 | G14: =MIN(F14,$B$4*B14) | H14: =E14+G14 | I14: 19270.865 | J14: =MIN(I14,H14) | K14: =MIN(MAX(J14*$B$5,$B$6),$B$7)*(J14>0) | L14: =MAX(0,J14-K14) | M14: the cap binds
A15: 331011f8-ce50-46ad-9aeb-03fffa6c8506 | B15: 1 | C15: 11.619808 | D15: 875.22564 | E15: =MIN(C15,$B$3)*D15 | F15: 20611.86 | G15: =MIN(F15,$B$4*B15) | H15: =E15+G15 | I15: 35189.116 | J15: =MIN(I15,H15) | K15: =MIN(MAX(J15*$B$5,$B$6),$B$7)*(J15>0) | L15: =MAX(0,J15-K15) | M15: the cap binds
A16: 36df7f1f-d454-4fd8-9751-1db3ad4e883a | B16: 1 | C16: 5.2549107 | D16: 1033.807 | E16: =MIN(C16,$B$3)*D16 | F16: 0 | G16: =MIN(F16,$B$4*B16) | H16: =E16+G16 | I16: 13180.269 | J16: =MIN(I16,H16) | K16: =MIN(MAX(J16*$B$5,$B$6),$B$7)*(J16>0) | L16: =MAX(0,J16-K16) | M16: the cap binds
A17: 3c9cb87a-ae7d-4616-b2f0-ffff94a2930b | B17: 1 | C17: 83.99693 | D17: 952.51889 | E17: =MIN(C17,$B$3)*D17 | F17: 0 | G17: =MIN(F17,$B$4*B17) | H17: =E17+G17 | I17: 80862.946 | J17: =MIN(I17,H17) | K17: =MIN(MAX(J17*$B$5,$B$6),$B$7)*(J17>0) | L17: =MAX(0,J17-K17) | M17: the cap binds
A18: 06953c1e-a185-4880-a3e8-203ab7d4220a | B18: 5 | C18: 31.561858 | D18: 1215.2551 | E18: =MIN(C18,$B$3)*D18 | F18: 0 | G18: =MIN(F18,$B$4*B18) | H18: =E18+G18 | I18: 35022.687 | J18: =MIN(I18,H18) | K18: =MIN(MAX(J18*$B$5,$B$6),$B$7)*(J18>0) | L18: =MAX(0,J18-K18) | M18: landslide, new wall built
A19: 0af1f540-21f2-4654-97ed-047e9a0d7e42 | B19: 1 | C19: 356.37881 | D19: 1845.735 | E19: =MIN(C19,$B$3)*D19 | F19: 0 | G19: =MIN(F19,$B$4*B19) | H19: =E19+G19 | I19: 13021.696 | J19: =MIN(I19,H19) | K19: =MIN(MAX(J19*$B$5,$B$6),$B$7)*(J19>0) | L19: =MAX(0,J19-K19) | M19: landslide, new wall built
A20: 0bc8522b-2de5-402b-b82e-ebb534151ee9 | B20: 4 | C20: 336.60416 | D20: 1750.1057 | E20: =MIN(C20,$B$3)*D20 | F20: 0 | G20: =MIN(F20,$B$4*B20) | H20: =E20+G20 | I20: 25993.905 | J20: =MIN(I20,H20) | K20: =MIN(MAX(J20*$B$5,$B$6),$B$7)*(J20>0) | L20: =MAX(0,J20-K20) | M20: landslide, new wall built
A21: 0fb3766f-33f4-4b9d-95c4-74dbfc6876dd | B21: 9 | C21: 34.126501 | D21: 2173.3146 | E21: =MIN(C21,$B$3)*D21 | F21: 0 | G21: =MIN(F21,$B$4*B21) | H21: =E21+G21 | I21: 31894.318 | J21: =MIN(I21,H21) | K21: =MIN(MAX(J21*$B$5,$B$6),$B$7)*(J21>0) | L21: =MAX(0,J21-K21) | M21: landslide, new wall built
A22: 0035a155-c4d3-4860-80e0-6c17481b3d61 | B22: 1 | C22: 0 | D22: 1125.8003 | E22: =MIN(C22,$B$3)*D22 | F22: 6586.8792 | G22: =MIN(F22,$B$4*B22) | H22: =E22+G22 | I22: 13769.255 | J22: =MIN(I22,H22) | K22: =MIN(MAX(J22*$B$5,$B$6),$B$7)*(J22>0) | L22: =MAX(0,J22-K22) | M22: damaged wall
A23: 00745333-cf86-4178-8cf6-cd6f9d7d5cbd | B23: 2 | C23: 0 | D23: 990.55498 | E23: =MIN(C23,$B$3)*D23 | F23: 14005.119 | G23: =MIN(F23,$B$4*B23) | H23: =E23+G23 | I23: 23804.7 | J23: =MIN(I23,H23) | K23: =MIN(MAX(J23*$B$5,$B$6),$B$7)*(J23>0) | L23: =MAX(0,J23-K23) | M23: damaged wall
A24: 00a83d76-9c9c-4d92-8d56-b16f1336cabb | B24: 1 | C24: 0 | D24: 909.01247 | E24: =MIN(C24,$B$3)*D24 | F24: 12561.542 | G24: =MIN(F24,$B$4*B24) | H24: =E24+G24 | I24: 23032.735 | J24: =MIN(I24,H24) | K24: =MIN(MAX(J24*$B$5,$B$6),$B$7)*(J24>0) | L24: =MAX(0,J24-K24) | M24: damaged wall
A25: 01b4d137-3ac2-408b-9de3-c572fc374ef4 | B25: 1 | C25: 472.24589 | D25: 1669.7247 | E25: =MIN(C25,$B$3)*D25 | F25: 19240.152 | G25: =MIN(F25,$B$4*B25) | H25: =E25+G25 | I25: 30975.841 | J25: =MIN(I25,H25) | K25: =MIN(MAX(J25*$B$5,$B$6),$B$7)*(J25>0) | L25: =MAX(0,J25-K25) | M25: damaged wall
... A33: 015ac9d8-763d-4df5-b585-423b129c132f | B33: 1 | C33: 0 | D33: 1772.0568 | E33: =MIN(C33,$B$3)*D33 | F33: 0 | G33: =MIN(F33,$B$4*B33) | H33: =E33+G33 | I33: 230 | J33: =MIN(I33,H33) | K33: =MIN(MAX(J33*$B$5,$B$6),$B$7)*(J33>0) | L33: =MAX(0,J33-K33) | M33: paid nothing, excess took it
A34: Total, these 20 claims | E34: =SUM(E14:E33) | F34: =SUM(F14:F33) | H34: =SUM(H14:H33) | I34: =SUM(I14:I33) | J34: =SUM(J14:J33) | K34: =SUM(K14:K33) | L34: =SUM(L14:L33)
A36: Black cells are live formulas and blue ones are inputs. Change a yellow setting above -- the excess rate, its ceiling, the area cap -- and every row and the totals follow. How a wall was priced is on the Repair cost tab.

Sheet Repair cost
A1: What is damaged, what it is worth, what repairing it costs
A2: One asset per block. Every dollar excludes GST until block D adds it once; the land values are market values, to which GST does not apply.
B4: A. Landslide land damage | O4: B. Retaining wall damage | V4: C. Liquefaction damage | AC4: D. What is paid
A5: Claim | B5: Evacuated land (m2) | C5: Inundated land (m2) | D5: Imminent damage (m2) - not modelled yet | E5: Total damaged land (m2) | F5: Land rate ($/m2) | G5: Value of damaged land ($) | H5: New RTW size | I5: New RTW height (m) | J5: New RTW length (m) | K5: New RTW to hold it ($) | L5: Spoil to clear (m3) | M5: Spoil removal ($) | N5: A. Landslide repair ($) | O5: What damaged it | P5: RTW size | Q5: RTW height (m) | R5: RTW length (m) | S5: RTW rate ($/m2) | T5: RTW undepreciated value ($) | U5: B. RTW replacement ($) | V5: Inundated land (m2) - not sent | W5: Evacuated land, with lateral spreading (m2) - not sent | X5: Liquefied land (m2) | Y5: Total insured land (m2) | Z5: Damage state | AA5: Value of liquefied land ($) | AB5: C. Liquefaction repair ($) | AC5: Dwellings | AD5: Professional fees ($) | AE5: Total repair, excl GST ($) | AF5: GST ($) | AG5: Culvert or bridge at its sub-cap ($) | AH5: Total repair, incl GST ($) | AI5: Cap: land value ($) | AJ5: Cap: RTW value ($) | AK5: Land cover cap ($) | AL5: Cost to pay ($) | AM5: Excess ($) | AN5: Settlement, incl GST ($) | AO5: Settlement, excl GST ($)
A6: 03dc0301-b79a-4927-9dc7-cd7e95fc9aaf | B6: 0 | C6: 3.9942764 | E6: 3.9942764 | F6: 906.91537 | G6: =MIN(E6,Calculation!$B$3)*F6 | I6: 0 | J6: 0 | K6: 0 | L6: 1.884367 | M6: 282.65505 | N6: =K6+M6 | O6: shaking | P6: medium | Q6: 1.75 | R6: 6.3131083 | S6: 798.8 | T6: 8825.0941 | U6: 11119.619 | X6: 0 | Y6: 159.42135 | Z6: 0 | AA6: =MIN(X6,Calculation!$B$3)*F6 | AB6: 0 | AC6: 1 | AD6: 5355 | AE6: =N6+U6+AB6+AD6 | AF6: =AE6*Calculation!$B$9 | AG6: 0 | AH6: =AE6+AF6+AG6 | AI6: =MAX(G6,AA6) | AJ6: =MIN(T6*(1+Calculation!$B$9),Calculation!$B$4*AC6) | AK6: =AI6+AJ6+AG6 | AL6: =MIN(AH6,AK6) | AM6: =MIN(MAX(AL6*Calculation!$B$5,Calculation!$B$6),Calculation!$B$7)*(AL6>0) | AN6: =MAX(0,AL6-AM6) | AO6: =AN6/(1+Calculation!$B$9)
A7: 331011f8-ce50-46ad-9aeb-03fffa6c8506 | B7: 11.619808 | C7: 0 | E7: 11.619808 | F7: 875.22564 | G7: =MIN(E7,Calculation!$B$3)*F7 | I7: 0 | J7: 0 | K7: 0 | L7: 0 | M7: 0 | N7: =K7+M7 | O7: shaking + evacuated | P7: large | Q7: 2.75 | R7: 8.159219 | S7: 798.8 | T7: 17923.356 | U7: 24734.232 | X7: 0 | Y7: 266.29142 | Z7: 0 | AA7: =MIN(X7,Calculation!$B$3)*F7 | AB7: 0 | AC7: 1 | AD7: 5865 | AE7: =N7+U7+AB7+AD7 | AF7: =AE7*Calculation!$B$9 | AG7: 0 | AH7: =AE7+AF7+AG7 | AI7: =MAX(G7,AA7) | AJ7: =MIN(T7*(1+Calculation!$B$9),Calculation!$B$4*AC7) | AK7: =AI7+AJ7+AG7 | AL7: =MIN(AH7,AK7) | AM7: =MIN(MAX(AL7*Calculation!$B$5,Calculation!$B$6),Calculation!$B$7)*(AL7>0) | AN7: =MAX(0,AL7-AM7) | AO7: =AN7/(1+Calculation!$B$9)
A8: 36df7f1f-d454-4fd8-9751-1db3ad4e883a | B8: 2.7399218 | C8: 5.2549107 | E8: 5.2549107 | F8: 1033.807 | G8: =MIN(E8,Calculation!$B$3)*F8 | H8: small | I8: 0.75 | J8: 7.2418855 | K8: 5496.382 | L8: 2.3648073 | M8: 354.7211 | N8: =K8+M8 | O8: wall present, undamaged | P8: none | Q8: 0 | R8: 0 | S8: 0 | T8: 0 | U8: 0 | X8: 0 | Y8: 420.23715 | Z8: 0 | AA8: =MIN(X8,Calculation!$B$3)*F8 | AB8: 0 | AC8: 1 | AD8: 5610 | AE8: =N8+U8+AB8+AD8 | AF8: =AE8*Calculation!$B$9 | AG8: 0 | AH8: =AE8+AF8+AG8 | AI8: =MAX(G8,AA8) | AJ8: =MIN(T8*(1+Calculation!$B$9),Calculation!$B$4*AC8) | AK8: =AI8+AJ8+AG8 | AL8: =MIN(AH8,AK8) | AM8: =MIN(MAX(AL8*Calculation!$B$5,Calculation!$B$6),Calculation!$B$7)*(AL8>0) | AN8: =MAX(0,AL8-AM8) | AO8: =AN8/(1+Calculation!$B$9)
A9: 3c9cb87a-ae7d-4616-b2f0-ffff94a2930b | B9: 4.8137986 | C9: 83.99693 | E9: 83.99693 | F9: 952.51889 | G9: =MIN(E9,Calculation!$B$3)*F9 | H9: large | I9: 2.75 | J9: 16.961245 | K9: 49346.864 | L9: 100.69161 | M9: 15103.742 | N9: =K9+M9 | O9: no wall on the property | P9: none | Q9: 0 | R9: 0 | S9: 0 | T9: 0 | U9: 0 | X9: 0 | Y9: 447.6237 | Z9: 0 | AA9: =MIN(X9,Calculation!$B$3)*F9 | AB9: 0 | AC9: 1 | AD9: 5865 | AE9: =N9+U9+AB9+AD9 | AF9: =AE9*Calculation!$B$9 | AG9: 0 | AH9: =AE9+AF9+AG9 | AI9: =MAX(G9,AA9) | AJ9: =MIN(T9*(1+Calculation!$B$9),Calculation!$B$4*AC9) | AK9: =AI9+AJ9+AG9 | AL9: =MIN(AH9,AK9) | AM9: =MIN(MAX(AL9*Calculation!$B$5,Calculation!$B$6),Calculation!$B$7)*(AL9>0) | AN9: =MAX(0,AL9-AM9) | AO9: =AN9/(1+Calculation!$B$9)
A10: 06953c1e-a185-4880-a3e8-203ab7d4220a | B10: 25.765802 | C10: 23.231989 | E10: 31.561858 | F10: 1215.2551 | G10: =MIN(E10,Calculation!$B$3)*F10 | H10: medium | I10: 1.75 | J10: 11.945043 | K10: 23076.946 | L10: 7.050431 | M10: 1057.5646 | N10: =K10+M10 | O10: no wall on the property | P10: none | Q10: 0 | R10: 0 | S10: 0 | T10: 0 | U10: 0 | X10: 0 | Y10: 50447.227 | Z10: 1 | AA10: =MIN(X10,Calculation!$B$3)*F10 | AB10: 200 | AC10: 5 | AD10: 6120 | AE10: =N10+U10+AB10+AD10 | AF10: =AE10*Calculation!$B$9 | AG10: 0 | AH10: =AE10+AF10+AG10 | AI10: =MAX(G10,AA10) | AJ10: =MIN(T10*(1+Calculation!$B$9),Calculation!$B$4*AC10) | AK10: =AI10+AJ10+AG10 | AL10: =MIN(AH10,AK10) | AM10: =MIN(MAX(AL10*Calculation!$B$5,Calculation!$B$6),Calculation!$B$7)*(AL10>0) | AN10: =MAX(0,AL10-AM10) | AO10: =AN10/(1+Calculation!$B$9)
A11: 0af1f540-21f2-4654-97ed-047e9a0d7e42 | B11: 5.6368954 | C11: 3.183434 | E11: 5.9031145 | F11: 1845.735 | G11: =MIN(E11,Calculation!$B$3)*F11 | H11: small | I11: 0.75 | J11: 7.4360193 | K11: 5387.1911 | L11: 0.5401544 | M11: 81.02316 | N11: =K11+M11 | O11: no wall on the property | P11: none | Q11: 0 | R11: 0 | S11: 0 | T11: 0 | U11: 0 | X11: 356.37881 | Y11: 356.37881 | Z11: 2 | AA11: =MIN(X11,Calculation!$B$3)*F11 | AB11: 500 | AC11: 1 | AD11: 5355 | AE11: =N11+U11+AB11+AD11 | AF11: =AE11*Calculation!$B$9 | AG11: 0 | AH11: =AE11+AF11+AG11 | AI11: =MAX(G11,AA11) | AJ11: =MIN(T11*(1+Calculation!$B$9),Calculation!$B$4*AC11) | AK11: =AI11+AJ11+AG11 | AL11: =MIN(AH11,AK11) | AM11: =MIN(MAX(AL11*Calculation!$B$5,Calculation!$B$6),Calculation!$B$7)*(AL11>0) | AN11: =MAX(0,AL11-AM11) | AO11: =AN11/(1+Calculation!$B$9)
A12: 0bc8522b-2de5-402b-b82e-ebb534151ee9 | B12: 15.489832 | C12: 8.5478471 | E12: 15.489832 | F12: 1750.1057 | G12: =MIN(E12,Calculation!$B$3)*F12 | H12: medium | I12: 1.75 | J12: 9.5659379 | K12: 15400.574 | L12: 4.0188101 | M12: 602.82151 | N12: =K12+M12 | O12: no wall on the property | P12: none | Q12: 0 | R12: 0 | S12: 0 | T12: 0 | U12: 0 | X12: 336.60416 | Y12: 336.60416 | Z12: 3 | AA12: =MIN(X12,Calculation!$B$3)*F12 | AB12: 1500 | AC12: 4 | AD12: 5100 | AE12: =N12+U12+AB12+AD12 | AF12: =AE12*Calculation!$B$9 | AG12: 0 | AH12: =AE12+AF12+AG12 | AI12: =MAX(G12,AA12) | AJ12: =MIN(T12*(1+Calculation!$B$9),Calculation!$B$4*AC12) | AK12: =AI12+AJ12+AG12 | AL12: =MIN(AH12,AK12) | AM12: =MIN(MAX(AL12*Calculation!$B$5,Calculation!$B$6),Calculation!$B$7)*(AL12>0) | AN12: =MAX(0,AL12-AM12) | AO12: =AN12/(1+Calculation!$B$9)
A13: 0fb3766f-33f4-4b9d-95c4-74dbfc6876dd | B13: 28.165983 | C13: 28.165983 | E13: 34.126501 | F13: 2173.3146 | G13: =MIN(E13,Calculation!$B$3)*F13 | H13: medium | I13: 1.75 | J13: 12.261538 | K13: 20727.341 | L13: 9.6789913 | M13: 1451.8487 | N13: =K13+M13 | O13: no wall on the property | P13: none | Q13: 0 | R13: 0 | S13: 0 | T13: 0 | U13: 0 | X13: 0 | Y13: 836.05273 | Z13: 1 | AA13: =MIN(X13,Calculation!$B$3)*F13 | AB13: 200 | AC13: 9 | AD13: 5355 | AE13: =N13+U13+AB13+AD13 | AF13: =AE13*Calculation!$B$9 | AG13: 0 | AH13: =AE13+AF13+AG13 | AI13: =MAX(G13,AA13) | AJ13: =MIN(T13*(1+Calculation!$B$9),Calculation!$B$4*AC13) | AK13: =AI13+AJ13+AG13 | AL13: =MIN(AH13,AK13) | AM13: =MIN(MAX(AL13*Calculation!$B$5,Calculation!$B$6),Calculation!$B$7)*(AL13>0) | AN13: =MAX(0,AL13-AM13) | AO13: =AN13/(1+Calculation!$B$9)
A14: 0035a155-c4d3-4860-80e0-6c17481b3d61 | B14: 0 | C14: 0 | E14: 0 | F14: 1125.8003 | G14: =MIN(E14,Calculation!$B$3)*F14 | I14: 0 | J14: 0 | K14: 0 | L14: 0 | M14: 0 | N14: =K14+M14 | O14: shaking | P14: small | Q14: 0.75 | R14: 6.2389397 | S14: 1224.08 | T14: 5727.721 | U14: 6873.2652 | X14: 0 | Y14: 155.69748 | Z14: 0 | AA14: =MIN(X14,Calculation!$B$3)*F14 | AB14: 0 | AC14: 1 | AD14: 5100 | AE14: =N14+U14+AB14+AD14 | AF14: =AE14*Calculation!$B$9 | AG14: 0 | AH14: =AE14+AF14+AG14 | AI14: =MAX(G14,AA14) | AJ14: =MIN(T14*(1+Calculation!$B$9),Calculation!$B$4*AC14) | AK14: =AI14+AJ14+AG14 | AL14: =MIN(AH14,AK14) | AM14: =MIN(MAX(AL14*Calculation!$B$5,Calculation!$B$6),Calculation!$B$7)*(AL14>0) | AN14: =MAX(0,AL14-AM14) | AO14: =AN14/(1+Calculation!$B$9)
A15: 00745333-cf86-4178-8cf6-cd6f9d7d5cbd | B15: 0 | C15: 0 | E15: 0 | F15: 990.55498 | G15: =MIN(E15,Calculation!$B$3)*F15 | I15: 0 | J15: 0 | K15: 0 | L15: 0 | M15: 0 | N15: =K15+M15 | O15: shaking | P15: medium | Q15: 1.75 | R15: 8.7118994 | S15: 798.8 | T15: 12178.364 | U15: 15344.739 | X15: 0 | Y15: 303.58877 | Z15: 0 | AA15: =MIN(X15,Calculation!$B$3)*F15 | AB15: 0 | AC15: 2 | AD15: 5355 | AE15: =N15+U15+AB15+AD15 | AF15: =AE15*Calculation!$B$9 | AG15: 0 | AH15: =AE15+AF15+AG15 | AI15: =MAX(G15,AA15) | AJ15: =MIN(T15*(1+Calculation!$B$9),Calculation!$B$4*AC15) | AK15: =AI15+AJ15+AG15 | AL15: =MIN(AH15,AK15) | AM15: =MIN(MAX(AL15*Calculation!$B$5,Calculation!$B$6),Calculation!$B$7)*(AL15>0) | AN15: =MAX(0,AL15-AM15) | AO15: =AN15/(1+Calculation!$B$9)
A16: 00a83d76-9c9c-4d92-8d56-b16f1336cabb | B16: 0 | C16: 0 | E16: 0 | F16: 909.01247 | G16: =MIN(E16,Calculation!$B$3)*F16 | I16: 0 | J16: 0 | K16: 0 | L16: 0 | M16: 0 | N16: =K16+M16 | O16: shaking | P16: medium | Q16: 1.75 | R16: 9.7043796 | S16: 643.19 | T16: 10923.08 | U16: 14418.465 | X16: 0 | Y16: 376.69993 | Z16: 0 | AA16: =MIN(X16,Calculation!$B$3)*F16 | AB16: 0 | AC16: 1 | AD16: 5610 | AE16: =N16+U16+AB16+AD16 | AF16: =AE16*Calculation!$B$9 | AG16: 0 | AH16: =AE16+AF16+AG16 | AI16: =MAX(G16,AA16) | AJ16: =MIN(T16*(1+Calculation!$B$9),Calculation!$B$4*AC16) | AK16: =AI16+AJ16+AG16 | AL16: =MIN(AH16,AK16) | AM16: =MIN(MAX(AL16*Calculation!$B$5,Calculation!$B$6),Calculation!$B$7)*(AL16>0) | AN16: =MAX(0,AL16-AM16) | AO16: =AN16/(1+Calculation!$B$9)
A17: 01b4d137-3ac2-408b-9de3-c572fc374ef4 | B17: 0 | C17: 0 | E17: 0 | F17: 1669.7247 | G17: =MIN(E17,Calculation!$B$3)*F17 | I17: 0 | J17: 0 | K17: 0 | L17: 0 | M17: 0 | N17: =K17+M17 | O17: shaking | P17: medium | Q17: 1.75 | R17: 10.86561 | S17: 879.87 | T17: 16730.567 | U17: 21080.514 | X17: 472.24589 | Y17: 472.24589 | Z17: 2 | AA17: =MIN(X17,Calculation!$B$3)*F17 | AB17: 500 | AC17: 1 | AD17: 5355 | AE17: =N17+U17+AB17+AD17 | AF17: =AE17*Calculation!$B$9 | AG17: 0 | AH17: =AE17+AF17+AG17 | AI17: =MAX(G17,AA17) | AJ17: =MIN(T17*(1+Calculation!$B$9),Calculation!$B$4*AC17) | AK17: =AI17+AJ17+AG17 | AL17: =MIN(AH17,AK17) | AM17: =MIN(MAX(AL17*Calculation!$B$5,Calculation!$B$6),Calculation!$B$7)*(AL17>0) | AN17: =MAX(0,AL17-AM17) | AO17: =AN17/(1+Calculation!$B$9)
A18: 0017e6f7-95ee-4d2a-8bff-569d98d70ec8 | B18: 0 | C18: 0 | E18: 0 | F18: 1908.0278 | G18: =MIN(E18,Calculation!$B$3)*F18 | I18: 0 | J18: 0 | K18: 0 | L18: 0 | M18: 0 | N18: =K18+M18 | O18: no wall on the property | P18: none | Q18: 0 | R18: 0 | S18: 0 | T18: 0 | U18: 0 | X18: 2824.0332 | Y18: 2824.0332 | Z18: 6 | AA18: =MIN(X18,Calculation!$B$3)*F18 | AB18: 4000 | AC18: 29 | AD18: 0 | AE18: =N18+U18+AB18+AD18 | AF18: =AE18*Calculation!$B$9 | AG18: 0 | AH18: =AE18+AF18+AG18 | AI18: =MAX(G18,AA18) | AJ18: =MIN(T18*(1+Calculation!$B$9),Calculation!$B$4*AC18) | AK18: =AI18+AJ18+AG18 | AL18: =MIN(AH18,AK18) | AM18: =MIN(MAX(AL18*Calculation!$B$5,Calculation!$B$6),Calculation!$B$7)*(AL18>0) | AN18: =MAX(0,AL18-AM18) | AO18: =AN18/(1+Calculation!$B$9)
A19: 00191a75-aed6-4265-a79b-faa275f0040c | B19: 0 | C19: 0 | E19: 0 | F19: 1891.5197 | G19: =MIN(E19,Calculation!$B$3)*F19 | I19: 0 | J19: 0 | K19: 0 | L19: 0 | M19: 0 | N19: =K19+M19 | O19: no wall on the property | P19: none | Q19: 0 | R19: 0 | S19: 0 | T19: 0 | U19: 0 | X19: 286.03721 | Y19: 286.03721 | Z19: 3 | AA19: =MIN(X19,Calculation!$B$3)*F19 | AB19: 1500 | AC19: 1 | AD19: 0 | AE19: =N19+U19+AB19+AD19 | AF19: =AE19*Calculation!$B$9 | AG19: 0 | AH19: =AE19+AF19+AG19 | AI19: =MAX(G19,AA19) | AJ19: =MIN(T19*(1+Calculation!$B$9),Calculation!$B$4*AC19) | AK19: =AI19+AJ19+AG19 | AL19: =MIN(AH19,AK19) | AM19: =MIN(MAX(AL19*Calculation!$B$5,Calculation!$B$6),Calculation!$B$7)*(AL19>0) | AN19: =MAX(0,AL19-AM19) | AO19: =AN19/(1+Calculation!$B$9)
A20: 001e2f9c-9846-4a4d-aff2-1de9e7b091c7 | B20: 0 | C20: 0 | E20: 0 | F20: 1603.4756 | G20: =MIN(E20,Calculation!$B$3)*F20 | I20: 0 | J20: 0 | K20: 0 | L20: 0 | M20: 0 | N20: =K20+M20 | O20: no wall on the property | P20: none | Q20: 0 | R20: 0 | S20: 0 | T20: 0 | U20: 0 | X20: 192.39876 | Y20: 192.39876 | Z20: 3 | AA20: =MIN(X20,Calculation!$B$3)*F20 | AB20: 1500 | AC20: 1 | AD20: 0 | AE20: =N20+U20+AB20+AD20 | AF20: =AE20*Calculation!$B$9 | AG20: 0 | AH20: =AE20+AF20+AG20 | AI20: =MAX(G20,AA20) | AJ20: =MIN(T20*(1+Calculation!$B$9),Calculation!$B$4*AC20) | AK20: =AI20+AJ20+AG20 | AL20: =MIN(AH20,AK20) | AM20: =MIN(MAX(AL20*Calculation!$B$5,Calculation!$B$6),Calculation!$B$7)*(AL20>0) | AN20: =MAX(0,AL20-AM20) | AO20: =AN20/(1+Calculation!$B$9)
A21: 0055aa62-333d-49e8-8a1b-4277448835ed | B21: 0 | C21: 0 | E21: 0 | F21: 1832.0435 | G21: =MIN(E21,Calculation!$B$3)*F21 | I21: 0 | J21: 0 | K21: 0 | L21: 0 | M21: 0 | N21: =K21+M21 | O21: no wall on the property | P21: none | Q21: 0 | R21: 0 | S21: 0 | T21: 0 | U21: 0 | X21: 212.76842 | Y21: 212.76842 | Z21: 2 | AA21: =MIN(X21,Calculation!$B$3)*F21 | AB21: 500 | AC21: 5 | AD21: 0 | AE21: =N21+U21+AB21+AD21 | AF21: =AE21*Calculation!$B$9 | AG21: 0 | AH21: =AE21+AF21+AG21 | AI21: =MAX(G21,AA21) | AJ21: =MIN(T21*(1+Calculation!$B$9),Calculation!$B$4*AC21) | AK21: =AI21+AJ21+AG21 | AL21: =MIN(AH21,AK21) | AM21: =MIN(MAX(AL21*Calculation!$B$5,Calculation!$B$6),Calculation!$B$7)*(AL21>0) | AN21: =MAX(0,AL21-AM21) | AO21: =AN21/(1+Calculation!$B$9)
A22: 002e15d9-b27f-4a99-b94d-703b11215eab | B22: 0 | C22: 0 | E22: 0 | F22: 816.21673 | G22: =MIN(E22,Calculation!$B$3)*F22 | I22: 0 | J22: 0 | K22: 0 | L22: 0 | M22: 0 | N22: =K22+M22 | O22: no wall on the property | P22: none | Q22: 0 | R22: 0 | S22: 0 | T22: 0 | U22: 0 | X22: 0 | Y22: 252.33664 | Z22: 0 | AA22: =MIN(X22,Calculation!$B$3)*F22 | AB22: 0 | AC22: 3 | AD22: 0 | AE22: =N22+U22+AB22+AD22 | AF22: =AE22*Calculation!$B$9 | AG22: 0 | AH22: =AE22+AF22+AG22 | AI22: =MAX(G22,AA22) | AJ22: =MIN(T22*(1+Calculation!$B$9),Calculation!$B$4*AC22) | AK22: =AI22+AJ22+AG22 | AL22: =MIN(AH22,AK22) | AM22: =MIN(MAX(AL22*Calculation!$B$5,Calculation!$B$6),Calculation!$B$7)*(AL22>0) | AN22: =MAX(0,AL22-AM22) | AO22: =AN22/(1+Calculation!$B$9)
A23: 0120d782-7901-4838-9ae8-012ec8626771 | B23: 0 | C23: 0 | E23: 0 | F23: 1691.8295 | G23: =MIN(E23,Calculation!$B$3)*F23 | I23: 0 | J23: 0 | K23: 0 | L23: 0 | M23: 0 | N23: =K23+M23 | O23: no wall on the property | P23: none | Q23: 0 | R23: 0 | S23: 0 | T23: 0 | U23: 0 | X23: 0 | Y23: 413.20273 | Z23: 1 | AA23: =MIN(X23,Calculation!$B$3)*F23 | AB23: 200 | AC23: 2 | AD23: 0 | AE23: =N23+U23+AB23+AD23 | AF23: =AE23*Calculation!$B$9 | AG23: 0 | AH23: =AE23+AF23+AG23 | AI23: =MAX(G23,AA23) | AJ23: =MIN(T23*(1+Calculation!$B$9),Calculation!$B$4*AC23) | AK23: =AI23+AJ23+AG23 | AL23: =MIN(AH23,AK23) | AM23: =MIN(MAX(AL23*Calculation!$B$5,Calculation!$B$6),Calculation!$B$7)*(AL23>0) | AN23: =MAX(0,AL23-AM23) | AO23: =AN23/(1+Calculation!$B$9)
A24: 012c131a-dea5-4ece-8e66-1e6f0f73959e | B24: 0 | C24: 0 | E24: 0 | F24: 1982.6859 | G24: =MIN(E24,Calculation!$B$3)*F24 | I24: 0 | J24: 0 | K24: 0 | L24: 0 | M24: 0 | N24: =K24+M24 | O24: no wall on the property | P24: none | Q24: 0 | R24: 0 | S24: 0 | T24: 0 | U24: 0 | X24: 0 | Y24: 185.62543 | Z24: 1 | AA24: =MIN(X24,Calculation!$B$3)*F24 | AB24: 200 | AC24: 1 | AD24: 0 | AE24: =N24+U24+AB24+AD24 | AF24: =AE24*Calculation!$B$9 | AG24: 0 | AH24: =AE24+AF24+AG24 | AI24: =MAX(G24,AA24) | AJ24: =MIN(T24*(1+Calculation!$B$9),Calculation!$B$4*AC24) | AK24: =AI24+AJ24+AG24 | AL24: =MIN(AH24,AK24) | AM24: =MIN(MAX(AL24*Calculation!$B$5,Calculation!$B$6),Calculation!$B$7)*(AL24>0) | AN24: =MAX(0,AL24-AM24) | AO24: =AN24/(1+Calculation!$B$9)
A25: 015ac9d8-763d-4df5-b585-423b129c132f | B25: 0 | C25: 0 | E25: 0 | F25: 1772.0568 | G25: =MIN(E25,Calculation!$B$3)*F25 | I25: 0 | J25: 0 | K25: 0 | L25: 0 | M25: 0 | N25: =K25+M25 | O25: no wall on the property | P25: none | Q25: 0 | R25: 0 | S25: 0 | T25: 0 | U25: 0 | X25: 0 | Y25: 345.7075 | Z25: 1 | AA25: =MIN(X25,Calculation!$B$3)*F25 | AB25: 200 | AC25: 1 | AD25: 0 | AE25: =N25+U25+AB25+AD25 | AF25: =AE25*Calculation!$B$9 | AG25: 0 | AH25: =AE25+AF25+AG25 | AI25: =MAX(G25,AA25) | AJ25: =MIN(T25*(1+Calculation!$B$9),Calculation!$B$4*AC25) | AK25: =AI25+AJ25+AG25 | AL25: =MIN(AH25,AK25) | AM25: =MIN(MAX(AL25*Calculation!$B$5,Calculation!$B$6),Calculation!$B$7)*(AL25>0) | AN25: =MAX(0,AL25-AM25) | AO25: =AN25/(1+Calculation!$B$9)
A29: How to read this tab
A30: Each of the first three blocks is one asset, and asks the same four questions about it: what is it, what is it worth, what would repairing it cost, and what does it contribute. Block D turns the three answers into one settlement. Every dollar is GST-exclusive until block D adds GST once, on the row marked 'GST'.
A31: The land values are the exception and are not GST-exclusive, because a market value is not a GST-bearing price. The Act caps cover at the market value of the damaged land, and the repair bill NHC pays carries GST, so the two sides of MIN(repair, cap) are compared on the GST-inclusive basis. Whether that is the intended reading is still open (Q-14).
A33: Empty columns, and why
A34: Imminent damage (block A) is not modelled yet. The agreed method is a second polygon of similar size centred on the same failure, its extra ground taken upslope to a new headscarp, with only the newly evacuated area counting. It belongs to vul and is calibrated off the claims reports.
A35: The three liquefaction extents (block C) are empty because vul sends liquefaction as a damage state with no footprint at all. Lateral spreading is being modelled as a magnification of the probability of states 4 to 6 near waterways, which moves a property's state rather than drawing an area -- so these columns may never be fillable in the form the heading implies.
A37: Assumptions behind each figure, to be confirmed
A38: A1. One wall stands on a property, so a claim is charged for one wall. Where a retaining wall is already there it is taken to be damaged and is replaced, and that replacement in block B is the whole of the wall cost -- block A is empty. Where there is no wall, one is invented to hold the ground and block B is empty. The two never both appear (decided 2026-09-29).
A39: A2. An invented wall is sized on the total damaged land -- the union of the evacuated and inundated footprints -- and on the deposit volume where an inundated depth gives one. Its length is twice the failure's depth plus 2 m at each end, never under 5 m. It is a remediation cost, not an asset, so it never reaches the cap: a wall that did not exist has no undepreciated value to contribute.
A40: A3. Spoil is cleared at the costing tool's own rate, 'Clear site: Load, cart and tip material', $150 per cubic metre excluding GST. The same volume also sets the earthworks rating, which is worth watching for a double count.
A41: B1. A wall already on the property is replaced rather than repaired: partial repair is about 1% of cases and is not modelled. Where the claim also has landslide ground, this replacement holds it, and no second wall is priced in block A.
A42: B2. Nothing says which of the tool's 29 construction types a wall is, so 30% are priced as Reinforced Concrete and the rest take one of four timber pole rates, drawn by hashing the wall id. The replacement carries the site multiplier and a 20% allowance for being built to a better standard than the one that failed; the undepreciated value carries neither, which is the whole of the difference between them.
... A49: The three site ratings that mark up a wall's cost -- construction access, earthworks and constructability -- are proxied off driveway length, inundated volume and ground slope. All bands are invented. Together they can move a wall cost by at most 30%.
